dingo/__init__.py
dingo/config/__init__.py
dingo/config/config.py
dingo/data/__init__.py
dingo/data/converter/__init__.py
dingo/data/converter/base.py
dingo/data/converter/img_utils.py
dingo/data/dataset/__init__.py
dingo/data/dataset/base.py
dingo/data/dataset/huggingface.py
dingo/data/dataset/local.py
dingo/data/dataset/spark.py
dingo/data/datasource/__init__.py
dingo/data/datasource/base.py
dingo/data/datasource/huggingface.py
dingo/data/datasource/local.py
dingo/data/datasource/s3.py
dingo/data/utils/__init__.py
dingo/data/utils/digit.py
dingo/data/utils/insecure_hash.py
dingo/exec/__init__.py
dingo/exec/base.py
dingo/exec/local.py
dingo/exec/spark.py
dingo/io/__init__.py
dingo/io/input/InputArgs.py
dingo/io/input/MetaData.py
dingo/io/input/__init__.py
dingo/io/output/ResultInfo.py
dingo/io/output/SummaryModel.py
dingo/io/output/__init__.py
dingo/model/__init__.py
dingo/model/model.py
dingo/model/modelres.py
dingo/model/llm/__init__.py
dingo/model/llm/base.py
dingo/model/llm/base_lmdeploy_apiclient.py
dingo/model/llm/base_openai.py
dingo/model/llm/classify_QR.py
dingo/model/llm/classify_topic.py
dingo/model/llm/detect_image_relevant.py
dingo/model/llm/detect_perspective.py
dingo/model/llm/detect_text_quality.py
dingo/model/llm/detect_text_quality_3h.py
dingo/model/llm/detect_text_quality_detail.py
dingo/model/prompt/__init__.py
dingo/model/prompt/base.py
dingo/model/prompt/prompt_QR.py
dingo/model/prompt/prompt_classify.py
dingo/model/prompt/prompt_common.py
dingo/model/prompt/prompt_image.py
dingo/model/prompt/prompt_text_language.py
dingo/model/prompt/prompt_text_quality.py
dingo/model/prompt/prompt_text_quality_3h.py
dingo/model/prompt/prompt_text_quality_multilan.py
dingo/model/response/__init__.py
dingo/model/response/response_class.py
dingo/model/rule/__init__.py
dingo/model/rule/base.py
dingo/model/rule/rule_common.py
dingo/model/rule/rule_image.py
dingo/model/rule/utils/__init__.py
dingo/model/rule/utils/detect_lang.py
dingo_client-1.3.1.dist-info/LICENSE
dingo_client-1.3.1.dist-info/METADATA
dingo_client-1.3.1.dist-info/WHEEL
dingo_client-1.3.1.dist-info/top_level.txt
dingo_client-1.3.1.dist-info/RECORD
