Metadata-Version: 2.2
Name: dingo-client
Version: 1.3.1
Summary: A Comprehensive Data Quality Evaluation Tool for Large Models
Home-page: https://github.com/DataEval/dingo
Author: Dingo
Classifier: Programming Language :: Python :: 3
Classifier: Operating System :: OS Independent
Requires-Python: >=3.10
License-File: LICENSE
Requires-Dist: boto3==1.28.43
Requires-Dist: botocore==1.31.43
Requires-Dist: chardet
Requires-Dist: datasets
Requires-Dist: fasttext-wheel==0.9.2
Requires-Dist: hanziconv
Requires-Dist: httpx==0.27.2
Requires-Dist: huggingface_hub
Requires-Dist: jieba
Requires-Dist: jsonlines
Requires-Dist: langid
Requires-Dist: openai==1.56.2
Requires-Dist: opencv-python
Requires-Dist: packaging
Requires-Dist: pandas
Requires-Dist: Pillow==9.4.0
Requires-Dist: prettytable
Requires-Dist: pyahocorasick
Requires-Dist: nltk
Requires-Dist: numpy==1.26.4
Requires-Dist: pydantic
Requires-Dist: requests
Requires-Dist: textstat
Requires-Dist: toml
Requires-Dist: transformers
Requires-Dist: wordninja==2.0.0
Requires-Dist: zhon
Requires-Dist: fastapi
Requires-Dist: uvicorn
Dynamic: author
Dynamic: classifier
Dynamic: description
Dynamic: description-content-type
Dynamic: home-page
Dynamic: requires-dist
Dynamic: requires-python
Dynamic: summary
